{"meta":{"schema_version":1,"version":"sha256:cf944afa9738f6033e340bdf51d74965d7985093ecccf75e1c818c4a0f0d66b9","snapshot_updated_at":"2026-03-22T06:07:40Z","snapshot_updated_date":"2026-03-22"},"columns":["site_id","site_name","country","data_hub","network","source_network","vegetation_type","first_year","last_year","download_link"],"rows":[["AR-CCg","Carlos Casares grassland","AR","AmeriFlux","AmeriFlux","AMF","GRA",2018,2024,"https://ftp.fluxdata.org/.ameriflux_downloads/FLUXNET/AMF_AR-CCg_FLUXNET_2018-2024_v1.3_r1.zip?=fluxnetshuttle"],["AR-TF1","Rio Moat bog","AR","AmeriFlux","AmeriFlux","AMF","WET",2016,2018,"https://ftp.fluxdata.org/.ameriflux_downloads/FLUXNET/AMF_AR-TF1_FLUXNET_2016-2018_v1.3_r1.zip?=fluxnetshuttle"],["AR-TF2","Rio Pipo bog","AR","AmeriFlux","AmeriFlux","AMF","WET",2016,2018,"https://ftp.fluxdata.org/.ameriflux_downloads/FLUXNET/AMF_AR-TF2_FLUXNET_2016-2018_v1.3_r1.zip?=fluxnetshuttle"],["BR-CST","Caatinga Serra Talhada","BR","AmeriFlux","AmeriFlux","AMF","DNF",2014,2015,"https://ftp.fluxdata.org/.ameriflux_downloads/FLUXNET/AMF_BR-CST_FLUXNET_2014-2015_v1.3_r1.zip?=fluxnetshuttle"],["CA-ARB","Attawapiskat River Bog","CA","AmeriFlux","AmeriFlux","AMF","WET",2011,2024,"https://ftp.fluxdata.org/.ameriflux_downloads/FLUXNET/AMF_CA-ARB_FLUXNET_2011-2024_v1.3_r1.zip?=fluxnetshuttle"],["CA-Ca1","British Columbia - 1949 Douglas-fir stand","CA","AmeriFlux","AmeriFlux;Fluxnet-Canada","AMF","ENF",1997,2010,"https://ftp.fluxdata.org/.ameriflux_downloads/FLUXNET/AMF_CA-Ca1_FLUXNET_1997-2010_v1.3_r1.zip?=fluxnetshuttle"],["CA-Ca2","British Columbia - Clearcut Douglas-fir stand (harvested winter 1999/2000)","CA","AmeriFlux","AmeriFlux;Fluxnet-Canada","AMF","ENF",2000,2010,"https://ftp.fluxdata.org/.ameriflux_downloads/FLUXNET/AMF_CA-Ca2_FLUXNET_2000-2010_v1.3_r1.zip?=fluxnetshuttle"],["CA-DB2","Delta Burns Bog 2","CA","AmeriFlux","AmeriFlux","AMF","WET",2019,2024,"https://ftp.fluxdata.org/.ameriflux_downloads/FLUXNET/AMF_CA-DB2_FLUXNET_2019-2024_v1.3_r1.zip?=fluxnetshuttle"],["CA-DBB","Delta Burns Bog","CA","AmeriFlux","AmeriFlux","AMF","WET",2015,2024,"https://ftp.fluxdata.org/.ameriflux_downloads/FLUXNET/AMF_CA-DBB_FLUXNET_2015-2024_v1.3_r1.zip?=fluxnetshuttle"],["CA-DSM","Delta Salt Marsh","CA","AmeriFlux","AmeriFlux","AMF","WET",2021,2024,"https://ftp.fluxdata.org/.ameriflux_downloads/FLUXNET/AMF_CA-DSM_FLUXNET_2021-2024_v1.3_r1.zip?=fluxnetshuttle"],["CA-EM1","Newdale Manitoba","CA","AmeriFlux","AmeriFlux","AMF","WET",2021,2023,"https://ftp.fluxdata.org/.ameriflux_downloads/FLUXNET/AMF_CA-EM1_FLUXNET_2021-2023_v1.3_r1.zip?=fluxnetshuttle"],["CA-EM2","Shoal Lake Manitoba","CA","AmeriFlux","AmeriFlux","AMF","WET",2021,2023,"https://ftp.fluxdata.org/.ameriflux_downloads/FLUXNET/AMF_CA-EM2_FLUXNET_2021-2023_v1.3_r1.zip?=fluxnetshuttle"],["CA-Gro","Ontario - Groundhog River, Boreal Mixedwood Forest","CA","AmeriFlux","AmeriFlux;Fluxnet-Canada;Phenocam","AMF","MF",2003,2014,"https://ftp.fluxdata.org/.ameriflux_downloads/FLUXNET/AMF_CA-Gro_FLUXNET_2003-2014_v1.3_r1.zip?=fluxnetshuttle"],["CA-MA1","Manitoba Agricultural Site 1","CA","AmeriFlux","AmeriFlux","AMF","CRO",2009,2011,"https://ftp.fluxdata.org/.ameriflux_downloads/FLUXNET/AMF_CA-MA1_FLUXNET_2009-2011_v1.3_r1.zip?=fluxnetshuttle"],["CA-MA2","Manitoba Agricultural Site 2","CA","AmeriFlux","AmeriFlux","AMF","CRO",2009,2011,"https://ftp.fluxdata.org/.ameriflux_downloads/FLUXNET/AMF_CA-MA2_FLUXNET_2009-2011_v1.3_r1.zip?=fluxnetshuttle"],["CA-MA3","Manitoba Agricultural Site 3","CA","AmeriFlux","AmeriFlux","AMF","GRA",2009,2011,"https://ftp.fluxdata.org/.ameriflux_downloads/FLUXNET/AMF_CA-MA3_FLUXNET_2009-2011_v1.3_r1.zip?=fluxnetshuttle"],["CA-Man","Manitoba - Northern Old Black Spruce (former BOREAS Northern Study Area)","CA","AmeriFlux","AmeriFlux;Fluxnet-Canada","AMF","ENF",1994,2008,"https://ftp.fluxdata.org/.ameriflux_downloads/FLUXNET/AMF_CA-Man_FLUXNET_1994-2008_v1.3_r1.zip?=fluxnetshuttle"],["CA-Mer","Ontario - Eastern Peatland, Mer Bleue","CA","AmeriFlux","AmeriFlux;Fluxnet-Canada;Phenocam","AMF","WET",1998,2020,"https://ftp.fluxdata.org/.ameriflux_downloads/FLUXNET/AMF_CA-Mer_FLUXNET_1998-2020_v1.3_r1.zip?=fluxnetshuttle"],["CA-Qc2","Quebec - 1975 Harvested Black Spruce (HBS75)","CA","AmeriFlux","AmeriFlux;Fluxnet-Canada","AMF","MF",2007,2010,"https://ftp.fluxdata.org/.ameriflux_downloads/FLUXNET/AMF_CA-Qc2_FLUXNET_2007-2010_v1.3_r1.zip?=fluxnetshuttle"],["CA-Qfo","Quebec - Eastern Boreal, Mature Black Spruce","CA","AmeriFlux","AmeriFlux;Fluxnet-Canada;Phenocam","AMF","ENF",2003,2010,"https://ftp.fluxdata.org/.ameriflux_downloads/FLUXNET/AMF_CA-Qfo_FLUXNET_2003-2010_v1.3_r1.zip?=fluxnetshuttle"],["CA-SCB","Scotty Creek Bog","CA","AmeriFlux","AmeriFlux","AMF","WET",2014,2019,"https://ftp.fluxdata.org/.ameriflux_downloads/FLUXNET/AMF_CA-SCB_FLUXNET_2014-2019_v1.3_r1.zip?=fluxnetshuttle"],["CA-TP3","Ontario - Turkey Point 1974 Plantation White Pine","CA","AmeriFlux","AmeriFlux;Fluxnet-Canada;Phenocam","AMF","ENF",2002,2023,"https://ftp.fluxdata.org/.ameriflux_downloads/FLUXNET/AMF_CA-TP3_FLUXNET_2002-2023_v1.3_r1.zip?=fluxnetshuttle"],["CA-TPD","Ontario - Turkey Point Mature Deciduous","CA","AmeriFlux","AmeriFlux;Fluxnet-Canada;Phenocam","AMF","DBF",2012,2023,"https://ftp.fluxdata.org/.ameriflux_downloads/FLUXNET/AMF_CA-TPD_FLUXNET_2012-2023_v1.3_r1.zip?=fluxnetshuttle"],["CL-ACF","Alerce Costero Forest","CL","AmeriFlux","AmeriFlux","AMF","ENF",2018,2020,"https://ftp.fluxdata.org/.ameriflux_downloads/FLUXNET/AMF_CL-ACF_FLUXNET_2018-2020_v1.3_r1.zip?=fluxnetshuttle"],["CL-SDF","Senda Darwin Forest","CL","AmeriFlux","AmeriFlux","AMF","EBF",2014,2021,"https://ftp.fluxdata.org/.ameriflux_downloads/FLUXNET/AMF_CL-SDF_FLUXNET_2014-2021_v1.3_r1.zip?=fluxnetshuttle"],["CL-SDP","Senda Darwin Peatland","CL","AmeriFlux","AmeriFlux","AMF","WET",2014,2021,"https://ftp.fluxdata.org/.ameriflux_downloads/FLUXNET/AMF_CL-SDP_FLUXNET_2014-2021_v1.3_r1.zip?=fluxnetshuttle"],["CR-Fsc","Filadelfia sugar cane cropland","CR","AmeriFlux","AmeriFlux","AMF","CRO",2015,2018,"https://ftp.fluxdata.org/.ameriflux_downloads/FLUXNET/AMF_CR-Fsc_FLUXNET_2015-2018_v1.3_r1.zip?=fluxnetshuttle"],["MX-Tes","Tesopaco, secondary tropical dry forest","MX","AmeriFlux","AmeriFlux;MexFlux","AMF","DBF",2004,2008,"https://ftp.fluxdata.org/.ameriflux_downloads/FLUXNET/AMF_MX-Tes_FLUXNET_2004-2008_v1.3_r1.zip?=fluxnetshuttle"],["PR-xLA","NEON Lajas Experimental Station (LAJA)","PR","AmeriFlux","AmeriFlux;NEON;Phenocam","AMF","GRA",2019,2024,"https://ftp.fluxdata.org/.ameriflux_downloads/FLUXNET/AMF_PR-xLA_FLUXNET_2019-2024_v1.3_r1.zip?=fluxnetshuttle"],["US-Bi1","Bouldin Island Alfalfa","US","AmeriFlux","AmeriFlux;Phenocam","AMF","CRO",2016,2024,"https://ftp.fluxdata.org/.ameriflux_downloads/FLUXNET/AMF_US-Bi1_FLUXNET_2016-2024_v1.3_r1.zip?=fluxnetshuttle"],["US-CdM","Cedar Mesa","US","AmeriFlux","AmeriFlux","AMF","WSA",2019,2024,"https://ftp.fluxdata.org/.ameriflux_downloads/FLUXNET/AMF_US-CdM_FLUXNET_2019-2024_v1.3_r1.zip?=fluxnetshuttle"],["US-ONA","Florida pine flatwoods","US","AmeriFlux","AmeriFlux;LTAR","AMF","GRA",2016,2022,"https://ftp.fluxdata.org/.ameriflux_downloads/FLUXNET/AMF_US-ONA_FLUXNET_2016-2022_v1.3_r1.zip?=fluxnetshuttle"],["US-RRC","Rice Rivers Center Marsh","US","AmeriFlux","AmeriFlux","AMF","WET",2022,2024,"https://ftp.fluxdata.org/.ameriflux_downloads/FLUXNET/AMF_US-RRC_FLUXNET_2022-2024_v1.3_r1.zip?=fluxnetshuttle"],["US-Ro5","Rosemount I18_South","US","AmeriFlux","AmeriFlux;Phenocam","AMF","CRO",2017,2024,"https://ftp.fluxdata.org/.ameriflux_downloads/FLUXNET/AMF_US-Ro5_FLUXNET_2017-2024_v1.3_r1.zip?=fluxnetshuttle"],["US-Ro6","Rosemount I18_North","US","AmeriFlux","AmeriFlux;Phenocam","AMF","CRO",2017,2024,"https://ftp.fluxdata.org/.ameriflux_downloads/FLUXNET/AMF_US-Ro6_FLUXNET_2017-2024_v1.3_r1.zip?=fluxnetshuttle"],["US-xAE","NEON Klemme Range Research Station (OAES)","US","AmeriFlux","AmeriFlux;NEON;Phenocam","AMF","GRA",2019,2024,"https://ftp.fluxdata.org/.ameriflux_downloads/FLUXNET/AMF_US-xAE_FLUXNET_2019-2024_v1.3_r1.zip?=fluxnetshuttle"],["US-xBA","NEON Barrow Environmental Observatory (BARR)","US","AmeriFlux","AmeriFlux;NEON;Phenocam","AMF","WET",2019,2024,"https://ftp.fluxdata.org/.ameriflux_downloads/FLUXNET/AMF_US-xBA_FLUXNET_2019-2024_v1.3_r1.zip?=fluxnetshuttle"],["US-xBN","NEON Caribou Creek - Poker Flats Watershed (BONA)","US","AmeriFlux","AmeriFlux;NEON;Phenocam","AMF","ENF",2019,2024,"https://ftp.fluxdata.org/.ameriflux_downloads/FLUXNET/AMF_US-xBN_FLUXNET_2019-2024_v1.3_r1.zip?=fluxnetshuttle"],["US-xBR","NEON Bartlett Experimental Forest (BART)","US","AmeriFlux","AmeriFlux;NEON;Phenocam","AMF","DBF",2019,2024,"https://ftp.fluxdata.org/.ameriflux_downloads/FLUXNET/AMF_US-xBR_FLUXNET_2019-2024_v1.3_r1.zip?=fluxnetshuttle"],["US-xCL","NEON LBJ National Grassland (CLBJ)","US","AmeriFlux","AmeriFlux;NEON;Phenocam","AMF","GRA",2019,2024,"https://ftp.fluxdata.org/.ameriflux_downloads/FLUXNET/AMF_US-xCL_FLUXNET_2019-2024_v1.3_r1.zip?=fluxnetshuttle"],["US-xDC","NEON Dakota Coteau Field School (DCFS)","US","AmeriFlux","AmeriFlux;NEON;Phenocam","AMF","GRA",2019,2024,"https://ftp.fluxdata.org/.ameriflux_downloads/FLUXNET/AMF_US-xDC_FLUXNET_2019-2024_v1.3_r1.zip?=fluxnetshuttle"],["US-xDJ","NEON Delta Junction (DEJU)","US","AmeriFlux","AmeriFlux;NEON;Phenocam","AMF","ENF",2019,2024,"https://ftp.fluxdata.org/.ameriflux_downloads/FLUXNET/AMF_US-xDJ_FLUXNET_2019-2024_v1.3_r1.zip?=fluxnetshuttle"],["US-xDS","NEON Disney Wilderness Preserve (DSNY)","US","AmeriFlux","AmeriFlux;NEON;Phenocam","AMF","CVM",2019,2024,"https://ftp.fluxdata.org/.ameriflux_downloads/FLUXNET/AMF_US-xDS_FLUXNET_2019-2024_v1.3_r1.zip?=fluxnetshuttle"],["US-xHE","NEON Healy (HEAL)","US","AmeriFlux","AmeriFlux;NEON;Phenocam","AMF","OSH",2019,2024,"https://ftp.fluxdata.org/.ameriflux_downloads/FLUXNET/AMF_US-xHE_FLUXNET_2019-2024_v1.3_r1.zip?=fluxnetshuttle"],["US-xJE","NEON Jones Ecological Research Center (JERC)","US","AmeriFlux","AmeriFlux;NEON;Phenocam","AMF","ENF",2019,2024,"https://ftp.fluxdata.org/.ameriflux_downloads/FLUXNET/AMF_US-xJE_FLUXNET_2019-2024_v1.3_r1.zip?=fluxnetshuttle"],["US-xNG","NEON Northern Great Plains Research Laboratory (NOGP)","US","AmeriFlux","AmeriFlux;NEON;Phenocam","AMF","GRA",2019,2024,"https://ftp.fluxdata.org/.ameriflux_downloads/FLUXNET/AMF_US-xNG_FLUXNET_2019-2024_v1.3_r1.zip?=fluxnetshuttle"],["US-xNW","NEON Niwot Ridge Mountain Research Station (NIWO)","US","AmeriFlux","AmeriFlux;NEON;Phenocam","AMF","ENF",2019,2024,"https://ftp.fluxdata.org/.ameriflux_downloads/FLUXNET/AMF_US-xNW_FLUXNET_2019-2024_v1.3_r1.zip?=fluxnetshuttle"],["US-xPU","NEON Pu'u Maka'ala Natural Area Reserve (PUUM)","US","AmeriFlux","AmeriFlux;NEON","AMF","EBF",2019,2024,"https://ftp.fluxdata.org/.ameriflux_downloads/FLUXNET/AMF_US-xPU_FLUXNET_2019-2024_v1.3_r1.zip?=fluxnetshuttle"],["US-xRM","NEON Rocky Mountain National Park, CASTNET (RMNP)","US","AmeriFlux","AmeriFlux;NEON;Phenocam","AMF","ENF",2019,2024,"https://ftp.fluxdata.org/.ameriflux_downloads/FLUXNET/AMF_US-xRM_FLUXNET_2019-2024_v1.3_r1.zip?=fluxnetshuttle"],["US-xSB","NEON Ordway-Swisher Biological Station (OSBS)","US","AmeriFlux","AmeriFlux;NEON;Phenocam","AMF","ENF",2019,2024,"https://ftp.fluxdata.org/.ameriflux_downloads/FLUXNET/AMF_US-xSB_FLUXNET_2019-2024_v1.3_r1.zip?=fluxnetshuttle"],["US-xTL","NEON Toolik (TOOL)","US","AmeriFlux","AmeriFlux;NEON;Phenocam","AMF","WET",2019,2024,"https://ftp.fluxdata.org/.ameriflux_downloads/FLUXNET/AMF_US-xTL_FLUXNET_2019-2024_v1.3_r1.zip?=fluxnetshuttle"],["US-xWR","NEON Wind River Experimental Forest (WREF)","US","AmeriFlux","AmeriFlux;NEON;Phenocam","AMF","ENF",2019,2024,"https://ftp.fluxdata.org/.ameriflux_downloads/FLUXNET/AMF_US-xWR_FLUXNET_2019-2024_v1.3_r1.zip?=fluxnetshuttle"],["AT-Mmg","Mieming","AT","ICOS","","EUF","ENF",2021,2024,"https://data.icos-cp.eu/licence_accept?ids=%5B%22SR8Y7XJE2CuwVkPh9WO7iXKF%22%5D"],["AT-PsM","Puergschachen Moor","AT","ICOS","","EUF","WET",2015,2019,"https://data.icos-cp.eu/licence_accept?ids=%5B%22STpBN0N9Df49Aabujg7yoJar%22%5D"],["AT-Zoe","Zoebelboden","AT","ICOS","","EUF","MF",2014,2024,"https://data.icos-cp.eu/licence_accept?ids=%5B%22cp3qmc9PDJw4kLwCX34YIr1M%22%5D"],["BE-Dor","Dorinne","BE","ICOS","","ICOS","GRA",2011,2024,"https://data.icos-cp.eu/licence_accept?ids=%5B%22geqYNPk-fvkZDGtnJI-sq1Je%22%5D"],["BE-Lcr","Lochristi","BE","ICOS","","EUF","DBF",2019,2022,"https://data.icos-cp.eu/licence_accept?ids=%5B%22oc2rvgUbNz-kUIeMsNmvNv8X%22%5D"],["BE-Lon","Lonzee","BE","ICOS","","ICOS","CRO",2004,2024,"https://data.icos-cp.eu/licence_accept?ids=%5B%221u2xQ5XcQoX0j2wJiZcyDP3M%22%5D"],["BE-Maa","Maasmechelen","BE","ICOS","","ICOS","CSH",2016,2024,"https://data.icos-cp.eu/licence_accept?ids=%5B%22ZG_uAsLMIT7yUsnXnJSB5Ufb%22%5D"],["BE-Vie","Vielsalm","BE","ICOS","","ICOS","MF",1996,2024,"https://data.icos-cp.eu/licence_accept?ids=%5B%22h7WL05ckcTEzgXiZaFsQDL4r%22%5D"],["BJ-Bfg","Bellefoungou","BJ","ICOS","","FLX","DBF",2008,2017,"https://data.icos-cp.eu/licence_accept?ids=%5B%223e0Uvz3eNFxHLxOGL6H7ciVC%22%5D"],["BJ-Nhu","Nalohou","BJ","ICOS","","FLX","SAV",2008,2017,"https://data.icos-cp.eu/licence_accept?ids=%5B%22lmKaXHkgzrf_23otyyDTLet5%22%5D"],["BW-Gum","Guma","BW","ICOS","","FLX","WET",2018,2020,"https://data.icos-cp.eu/licence_accept?ids=%5B%224tYejpkp-7QNMRnCzgTb9TY1%22%5D"],["BW-Nxr","Nxaraga","BW","ICOS","","FLX","GRA",2019,2020,"https://data.icos-cp.eu/licence_accept?ids=%5B%22OAWAcJkAaBET5Vn-Kx2tRvsb%22%5D"],["CD-Ygb","Yangambi","CD","ICOS","","ICOS","MF",2020,2024,"https://data.icos-cp.eu/licence_accept?ids=%5B%22Y_4oHTr_yfOSLhV2_swVropx%22%5D"],["CH-Aws","Alp Weissenstein","CH","ICOS","","EUF","GRA",2006,2024,"https://data.icos-cp.eu/licence_accept?ids=%5B%22quYooZm1POt6BTN6jvcIeZXb%22%5D"],["CH-Crs","Cressier","CH","ICOS","","EUF","GRA",2015,2016,"https://data.icos-cp.eu/licence_accept?ids=%5B%22imYdB4O0vIcmT-V5Xecz4Ww6%22%5D"],["CH-Dav","Davos","CH","ICOS","","ICOS","ENF",1997,2024,"https://data.icos-cp.eu/licence_accept?ids=%5B%22eHcoHNvdn-kHLqQoJbyUs0Yq%22%5D"],["CH-For","Forel","CH","ICOS","","EUF","CRO",2024,2024,"https://data.icos-cp.eu/licence_accept?ids=%5B%22oeTz7nJRUzGjcXqrVNE6tvin%22%5D"],["CH-Fru","Fruebuel","CH","ICOS","","EUF","GRA",2005,2024,"https://data.icos-cp.eu/licence_accept?ids=%5B%22xnRKIWdx6isC5GLqv_pHq5hU%22%5D"],["CH-Lae","Laegern","CH","ICOS","","EUF","MF",2004,2024,"https://data.icos-cp.eu/licence_accept?ids=%5B%22V_BAvTqbUIgSItmCcoHgP3Vy%22%5D"],["CH-Oe3","Oensingen extensive grassland","CH","ICOS","","EUF","GRA",2002,2011,"https://data.icos-cp.eu/licence_accept?ids=%5B%22QDwt2sFctYCIe0fLyRCIh497%22%5D"],["CH-Rh1","Ruethi peatland reference","CH","ICOS","","EUF","GRA",2018,2021,"https://data.icos-cp.eu/licence_accept?ids=%5B%22dvdiSGaj5yT3Cv3bSaKktRf5%22%5D"],["CH-Rh2","Ruethi peatland covered","CH","ICOS","","EUF","GRA",2018,2021,"https://data.icos-cp.eu/licence_accept?ids=%5B%22s29xGnt-hLzMlal-qo4i1iwb%22%5D"],["CH-Rtb","Rietholzbach","CH","ICOS","","EUF","GRA",2009,2022,"https://data.icos-cp.eu/licence_accept?ids=%5B%22ZSw7OruD5oGCPKwcw5aAC563%22%5D"],["CH-Tnk","Tanikon","CH","ICOS","","EUF","CRO",2024,2024,"https://data.icos-cp.eu/licence_accept?ids=%5B%22mkSJOp0Dw6pVHTYytNO2XjZW%22%5D"],["CN-Ash","Ailaoshan","CN","ICOS","","CNF","EBF",2009,2019,"https://data.icos-cp.eu/licence_accept?ids=%5B%221GvgqlnWHAEUQM5bFSqOCuYx%22%5D"],["CN-BeO","Beijing Olympic Forest Park","CN","ICOS","","CNF","MF",2012,2020,"https://data.icos-cp.eu/licence_accept?ids=%5B%221WNNhSlLFohjI_XuZI8-i6OP%22%5D"],["CN-Din","Dinghushan","CN","ICOS","","CNF","EBF",2010,2020,"https://data.icos-cp.eu/licence_accept?ids=%5B%22OAl_oKIuBTMvDJUVtKSBjFqi%22%5D"],["CN-Ha2","Haibei Shrubland","CN","ICOS","","CNF","OSH",2011,2019,"https://data.icos-cp.eu/licence_accept?ids=%5B%22CvtPWnBK5rqLfwp2Hicw_ffI%22%5D"],["CN-HaM","Haibei Alpine Tibet site","CN","ICOS","","JPF","GRA",2001,2014,"https://data.icos-cp.eu/licence_accept?ids=%5B%22eHxCM4Gfk3Wo-yA1sym5lBRo%22%5D"],["CN-Lsh","Laoshan","CN","ICOS","","JPF","DNF",2002,2006,"https://data.icos-cp.eu/licence_accept?ids=%5B%22eEffx70YefN_2F5Yx_sowWVR%22%5D"],["CN-Wnb","Wulanbuhe","CN","ICOS","","CNF","BSV",2021,2021,"https://data.icos-cp.eu/licence_accept?ids=%5B%22Idhv24AYZaeHtpqwqZ2rHemS%22%5D"],["CN-Yuc","Yucheng","CN","ICOS","","CNF","CRO",2011,2020,"https://data.icos-cp.eu/licence_accept?ids=%5B%22KOKIvzQXyRWnpE1SiJa2-m-1%22%5D"],["CR-AqC","Aquiares Coffee-Flux","CR","ICOS","","FLX","EBF",2009,2016,"https://data.icos-cp.eu/licence_accept?ids=%5B%22yRjv2loTLxMX5_elU4L2aqKw%22%5D"],["CZ-BK1","Bily Kriz forest","CZ","ICOS","","ICOS","ENF",2004,2024,"https://data.icos-cp.eu/licence_accept?ids=%5B%22KiFUcCsC30gKhoS-4oJf5__f%22%5D"],["CZ-KrP","Kresin u Pacova","CZ","ICOS","","EUF","CRO",2014,2023,"https://data.icos-cp.eu/licence_accept?ids=%5B%22nMA34HofEPJou2VKmDMTBo_9%22%5D"],["CZ-LnG","Lanzhot Grassland","CZ","ICOS","","EUF","GRA",2019,2024,"https://data.icos-cp.eu/licence_accept?ids=%5B%22cezPci33oJjpbkjDF47P8YIK%22%5D"],["CZ-Lnz","Lanzhot","CZ","ICOS","","ICOS","DBF",2015,2024,"https://data.icos-cp.eu/licence_accept?ids=%5B%22B2BjRQCUXetA0_vGI3x7WFUJ%22%5D"],["CZ-RAJ","Rajec","CZ","ICOS","","EUF","ENF",2012,2024,"https://data.icos-cp.eu/licence_accept?ids=%5B%22LlmTy3u9548FEMXEW59RiWpY%22%5D"],["CZ-Stn","Stitna","CZ","ICOS","","EUF","DBF",2010,2024,"https://data.icos-cp.eu/licence_accept?ids=%5B%22CM9ZMyBcfqBoKkmLPUDwiyMo%22%5D"],["CZ-wet","Trebon","CZ","ICOS","","ICOS","WET",2006,2024,"https://data.icos-cp.eu/licence_accept?ids=%5B%22r4kitQikcZG6sLZsHDmHf8Ks%22%5D"],["DE-Akm","Anklam","DE","ICOS","","EUF","WET",2009,2024,"https://data.icos-cp.eu/licence_accept?ids=%5B%22ibp-j16L3n3PSkD62K99WL_w%22%5D"],["DE-Amv","Amtsvenn","DE","ICOS","","ICOS","WET",2023,2024,"https://data.icos-cp.eu/licence_accept?ids=%5B%22Z1HD_OQWjwEXa0SSjuDuV1lD%22%5D"],["DE-Brs","Braunschweig","DE","ICOS","","ICOS","CRO",2023,2024,"https://data.icos-cp.eu/licence_accept?ids=%5B%222xakSoRK-wV1p54jFz4OvoRW%22%5D"],["DE-Etn","Ettenheim","DE","ICOS","","EUF","DBF",2024,2024,"https://data.icos-cp.eu/licence_accept?ids=%5B%22timq13anOgu_cC9YrhwCaa1K%22%5D"],["DE-Fen","Fendt","DE","ICOS","","ICOS","GRA",2023,2024,"https://data.icos-cp.eu/licence_accept?ids=%5B%22iP6bxAqxISmcVJ-L-k-t6rI8%22%5D"],["DE-Geb","Gebesee","DE","ICOS","","ICOS","CRO",2020,2024,"https://data.icos-cp.eu/licence_accept?ids=%5B%22jFkfMT_3ZahqoODz-R82VeUG%22%5D"],["DE-Gri","Grillenburg","DE","ICOS","","ICOS","GRA",2004,2024,"https://data.icos-cp.eu/licence_accept?ids=%5B%22H0WNTp4g4beCHZLD5k_u1SJ5%22%5D"],["DE-GsB","Grosses Bruch","DE","ICOS","","ICOS","GRA",2015,2024,"https://data.icos-cp.eu/licence_accept?ids=%5B%22OhUhfq6ZoSPv26JDuxzBszGu%22%5D"],["DE-Gwg","Graswang","DE","ICOS","","ICOS","GRA",2023,2024,"https://data.icos-cp.eu/licence_accept?ids=%5B%22GPtUsX3eLBhx-c2kGtz1zjZ-%22%5D"],["DE-Hai","Hainich","DE","ICOS","","ICOS","DBF",2000,2024,"https://data.icos-cp.eu/licence_accept?ids=%5B%22rOKIh2gg8tEExEelC67ZCp9q%22%5D"],["DE-Har","Hartheim","DE","ICOS","","ICOS","ENF",2020,2024,"https://data.icos-cp.eu/licence_accept?ids=%5B%22RMAJ-gFOgcGACadN_gZG_GqU%22%5D"],["DE-HoH","Hohes Holz","DE","ICOS","","ICOS","DBF",2015,2024,"https://data.icos-cp.eu/licence_accept?ids=%5B%22-aRYvkkX6D6wd2ijWclesXaK%22%5D"],["DE-Hzd","Hetzdorf","DE","ICOS","","ICOS","DBF",2022,2024,"https://data.icos-cp.eu/licence_accept?ids=%5B%22uq6kULT1EqxHKftJz-CqeaJa%22%5D"],["DE-Kli","Klingenberg","DE","ICOS","","ICOS","CRO",2018,2024,"https://data.icos-cp.eu/licence_accept?ids=%5B%22ViYMPdxbY25optpqiQ7OVgXN%22%5D"],["DE-Msr","Mooseurach","DE","ICOS","","ICOS","ENF",2020,2024,"https://data.icos-cp.eu/licence_accept?ids=%5B%22FYr5igpqgstIKkMu0YL-eKyI%22%5D"],["DE-Obe","Oberbarenburg","DE","ICOS","","EUF","ENF",2008,2024,"https://data.icos-cp.eu/licence_accept?ids=%5B%22mk-YBqXT0YwbluI9V726yD2d%22%5D"],["DE-Rns","Reinshof","DE","ICOS","","EUF","CRO",2021,2024,"https://data.icos-cp.eu/licence_accept?ids=%5B%22T08mrGq_-E_H2EIzKejmRpFA%22%5D"],["DE-RuC","Wustebach Clearcut","DE","ICOS","","EUF","OSH",2013,2024,"https://data.icos-cp.eu/licence_accept?ids=%5B%22MKtmPmXNZnCQc-p38RBQGATH%22%5D"],["DE-RuM","Merzenhausen","DE","ICOS","","EUF","CRO",2011,2019,"https://data.icos-cp.eu/licence_accept?ids=%5B%22u8eIM1nL0KdiWr-MLixNMsMS%22%5D"],["DE-RuR","Rollesbroich","DE","ICOS","","ICOS","GRA",2011,2024,"https://data.icos-cp.eu/licence_accept?ids=%5B%22MoiyY0KjXITz5V_oFs-x9bUj%22%5D"],["DE-RuS","Selhausen Juelich","DE","ICOS","","ICOS","CRO",2011,2024,"https://data.icos-cp.eu/licence_accept?ids=%5B%229m1zuO-nvw0zGnEdt0qo3Xzw%22%5D"],["DE-RuW","Wustebach","DE","ICOS","","ICOS","ENF",2011,2024,"https://data.icos-cp.eu/licence_accept?ids=%5B%22BytRjI_RJ0pRtLQCYfnb2Sd1%22%5D"],["DE-SbM","Sonnenberger Moor","DE","ICOS","","EUF","WET",2023,2024,"https://data.icos-cp.eu/licence_accept?ids=%5B%22JeVgt8rDc-YmluX84aD3xarU%22%5D"],["DE-Tha","Tharandt","DE","ICOS","","ICOS","ENF",1996,2024,"https://data.icos-cp.eu/licence_accept?ids=%5B%22ffjFRTBfditjn_0A4exzi5K8%22%5D"],["DK-Gds","Gludsted Plantage","DK","ICOS","","ICOS","ENF",2020,2022,"https://data.icos-cp.eu/licence_accept?ids=%5B%22vDQDn0hIxnz9gRAIc3duWbUE%22%5D"],["DK-RCW","Riso Campus Willow","DK","ICOS","","ICOS","DBF",2023,2024,"https://data.icos-cp.eu/licence_accept?ids=%5B%22m0GlLgv0gcrx3ujxm3uDVWpq%22%5D"],["DK-Skj","Skjern","DK","ICOS","","ICOS","WET",2020,2022,"https://data.icos-cp.eu/licence_accept?ids=%5B%22JPkhq8xhlXF20Cijd7pHUd-T%22%5D"],["DK-Sor","Soroe","DK","ICOS","","ICOS","DBF",1996,2024,"https://data.icos-cp.eu/licence_accept?ids=%5B%22lwXfRUVQCnuq5OcIe-F6tpib%22%5D"],["DK-Vng","Voulundgaard","DK","ICOS","","ICOS","CRO",2020,2023,"https://data.icos-cp.eu/licence_accept?ids=%5B%22SdbEo5oQOf__w-zjUCIB3EOL%22%5D"],["EE-Stg","Soontaga Forest Station","EE","ICOS","","EUF","ENF",2016,2024,"https://data.icos-cp.eu/licence_accept?ids=%5B%22C4Y455t1rGorFhBAkA5CiOXw%22%5D"],["ES-Agu","Aguamarga","ES","ICOS","","EUF","OSH",2006,2024,"https://data.icos-cp.eu/licence_accept?ids=%5B%22smUITWSfoJ6VoyqONgDBxTSn%22%5D"],["ES-Cnd","Conde","ES","ICOS","","EUF","WSA",2014,2021,"https://data.icos-cp.eu/licence_accept?ids=%5B%22ak3chQKBZovcC1AIpPf0aaJw%22%5D"],["ES-Crg","Caroig","ES","ICOS","","EUF","CSH",2021,2024,"https://data.icos-cp.eu/licence_accept?ids=%5B%22OuvCtRGBok2ZxUrKwXIP5LDY%22%5D"],["ES-Gdn","Guadiana","ES","ICOS","","EUF","SAV",2014,2021,"https://data.icos-cp.eu/licence_accept?ids=%5B%22EhJy8Xkd_vyJfhWOz3TNnFg-%22%5D"],["ES-HdD","Hinojosa del Duque","ES","ICOS","","EUF","SAV",2024,2024,"https://data.icos-cp.eu/licence_accept?ids=%5B%22w-KQ8NQ2IIyy_hF0LeeyY5EY%22%5D"],["ES-HeB","Hell\u00edn Burnt","ES","ICOS","","EUF","ENF",2019,2024,"https://data.icos-cp.eu/licence_accept?ids=%5B%22K1e9bqWUrsIlqHjlDzbl2VzM%22%5D"],["ES-Hen","Hellin","ES","ICOS","","EUF","ENF",2019,2024,"https://data.icos-cp.eu/licence_accept?ids=%5B%22MFHVWXPN9W_gfpI8fA4UtBVf%22%5D"],["ES-LM1","Majadas del Tietar North","ES","ICOS","","EUF","SAV",2014,2024,"https://data.icos-cp.eu/licence_accept?ids=%5B%229c9e--DRFTTyhtl6c0lcA3O6%22%5D"],["ES-LM2","Majadas del Tietar South","ES","ICOS","","EUF","SAV",2014,2024,"https://data.icos-cp.eu/licence_accept?ids=%5B%22CgWe1iCQaO3oYYxgSMEe1BSq%22%5D"],["ES-LMa","Las Majadas de Tietar","ES","ICOS","","ICOS","SAV",2020,2024,"https://data.icos-cp.eu/licence_accept?ids=%5B%22MSnF-sfvP507KrXcu5yl6LAx%22%5D"],["ES-Mcd","Moncada","ES","ICOS","","EUF","EBF",2018,2024,"https://data.icos-cp.eu/licence_accept?ids=%5B%22jyX3FQLrXu_wjllntwoO10IQ%22%5D"],["ES-Mzn","Manzanera","ES","ICOS","","EUF","EBF",2023,2024,"https://data.icos-cp.eu/licence_accept?ids=%5B%22HPlYEFEhMzxWYOTC7Ch8Ku5a%22%5D"],["ES-Pzb","Pozoblanco","ES","ICOS","","EUF","GRA",2020,2024,"https://data.icos-cp.eu/licence_accept?ids=%5B%227xwSGufRWY7Duyrf11N282pK%22%5D"],["ES-TzM","Tarazona de la Mancha","ES","ICOS","","EUF","DBF",2020,2024,"https://data.icos-cp.eu/licence_accept?ids=%5B%22gu5gauPM7ynjb6T28S4OY_sW%22%5D"],["ES-VDA","Vall d Alinya (Lleida)","ES","ICOS","","EUF","GRA",2022,2024,"https://data.icos-cp.eu/licence_accept?ids=%5B%22mLCP7JnLuR2woC45y23wPdGC%22%5D"],["FI-Ant","Anttila","FI","ICOS","","ICOS","CRO",2022,2022,"https://data.icos-cp.eu/licence_accept?ids=%5B%22WfnJvocMuoIL6hVB8mRB3XxS%22%5D"],["FI-Hyy","Hyytiala","FI","ICOS","","ICOS","ENF",1997,2024,"https://data.icos-cp.eu/licence_accept?ids=%5B%22pIDsMGxYyXTg31dHecNO55Nq%22%5D"],["FI-Ken","Kenttarova","FI","ICOS","","ICOS","ENF",2018,2024,"https://data.icos-cp.eu/licence_accept?ids=%5B%22BhlqiN95ECtoSXoxmf0Q4V35%22%5D"],["FI-Let","Lettosuo","FI","ICOS","","ICOS","ENF",2009,2024,"https://data.icos-cp.eu/licence_accept?ids=%5B%22DklI-LaynvPoGMvnIbInqLrw%22%5D"],["FI-Nsv","Naarasneva","FI","ICOS","","EUF","CVM",2021,2024,"https://data.icos-cp.eu/licence_accept?ids=%5B%22cSm1qTXbblwvWpF9j1Oow7qX%22%5D"],["FI-Pap","Pappilansuo","FI","ICOS","","EUF","CRO",2022,2022,"https://data.icos-cp.eu/licence_accept?ids=%5B%22u2xUfhEZCOWwWb3gVywfqYw_%22%5D"],["FI-Qvd","Qvidja","FI","ICOS","","EUF","CRO",2018,2023,"https://data.icos-cp.eu/licence_accept?ids=%5B%22UuvYrldK3v4VzDgfH6nC0ed7%22%5D"],["FI-Rk2","Ranskalankorpi","FI","ICOS","","EUF","ENF",2020,2023,"https://data.icos-cp.eu/licence_accept?ids=%5B%22Agmj31O2_U5UxIfjk_idGdLg%22%5D"],["FI-Ruk","Ruukki","FI","ICOS","","EUF","CRO",2020,2023,"https://data.icos-cp.eu/licence_accept?ids=%5B%22TYPI56oF2JQVeXc0g4SU60It%22%5D"],["FI-Sar","Sarkisuo","FI","ICOS","","EUF","CRO",2022,2022,"https://data.icos-cp.eu/licence_accept?ids=%5B%22xUETR-0OEq8u2S5UUHl8sLm_%22%5D"],["FI-Sii","Siikaneva","FI","ICOS","","ICOS","WET",2018,2024,"https://data.icos-cp.eu/licence_accept?ids=%5B%22mkbfyrZKqg3Djz0tW1rRap1c%22%5D"],["FI-Sod","Sodankyla","FI","ICOS","","ICOS","ENF",2023,2024,"https://data.icos-cp.eu/licence_accept?ids=%5B%22TNkSnk2tWf7rkMpSQ2Dtf8FI%22%5D"],["FI-Var","Varrio","FI","ICOS","","ICOS","ENF",2016,2024,"https://data.icos-cp.eu/licence_accept?ids=%5B%22Ve8588DeHh2Y-t-dtZGWggl6%22%5D"],["FR-Aur","Aurade","FR","ICOS","","ICOS","CRO",2005,2024,"https://data.icos-cp.eu/licence_accept?ids=%5B%22R0Wn1kGceDx6Zq8pJq_typhu%22%5D"],["FR-Bil","Bilos","FR","ICOS","","ICOS","ENF",2014,2024,"https://data.icos-cp.eu/licence_accept?ids=%5B%22Qa701KsgkCkpYT4vev--kpOk%22%5D"],["FR-CLt","Col du Lautaret","FR","ICOS","","ICOS","GRA",2019,2024,"https://data.icos-cp.eu/licence_accept?ids=%5B%22mbWVxsxcn7lbSZmVE08_nIUR%22%5D"],["FR-EM2","Estrees-Mons A28","FR","ICOS","","ICOS","CRO",2017,2024,"https://data.icos-cp.eu/licence_accept?ids=%5B%22XylBXyJlRDxIhbqaNsGdapw2%22%5D"],["FR-FBn","Font-Blanche","FR","ICOS","","ICOS","ENF",2008,2024,"https://data.icos-cp.eu/licence_accept?ids=%5B%22dw5JqZoWiNVw0JQS-QXykPY6%22%5D"],["FR-Fon","Fontainebleau-Barbeau","FR","ICOS","","ICOS","DBF",2019,2024,"https://data.icos-cp.eu/licence_accept?ids=%5B%22vgMluaOupOEt-hzl3RWXI99X%22%5D"],["FR-Gri","Grignon","FR","ICOS","","ICOS","CRO",2004,2024,"https://data.icos-cp.eu/licence_accept?ids=%5B%22_WcCYfVZLDpg4Gz-RlhwVX6Y%22%5D"],["FR-Hes","Hesse","FR","ICOS","","ICOS","DBF",1997,2024,"https://data.icos-cp.eu/licence_accept?ids=%5B%22762ZAgt8A5AGDMT1ry74n13K%22%5D"],["FR-LGt","La Guette","FR","ICOS","","ICOS","WET",2017,2024,"https://data.icos-cp.eu/licence_accept?ids=%5B%22j0j6eVryKF77_tfyxVLMNM31%22%5D"],["FR-Lam","Lamasquere","FR","ICOS","","ICOS","CRO",2021,2024,"https://data.icos-cp.eu/licence_accept?ids=%5B%22zwxh7ZEI7AWEJOF5ggdX2bpK%22%5D"],["FR-Lqu","Laqueuille","FR","ICOS","","ICOS","GRA",2022,2024,"https://data.icos-cp.eu/licence_accept?ids=%5B%22FT09cB-tv2MKDSSw1R_JXBJx%22%5D"],["FR-Lus","Lusignan","FR","ICOS","","ICOS","GRA",2022,2024,"https://data.icos-cp.eu/licence_accept?ids=%5B%22S_NN3abNF1zutV6hnPOuCupl%22%5D"],["FR-Mau","Mauzac","FR","ICOS","","EUF","GRA",2005,2011,"https://data.icos-cp.eu/licence_accept?ids=%5B%22ebGKrL-UajXA0SkdfSt100r9%22%5D"],["FR-Mej","Mejusseaume","FR","ICOS","","ICOS","GRA",2019,2024,"https://data.icos-cp.eu/licence_accept?ids=%5B%2289dJgrylR97XwCZTAHP5qw5a%22%5D"],["FR-Nzn","Naizin","FR","ICOS","","EUF","GRA",2016,2024,"https://data.icos-cp.eu/licence_accept?ids=%5B%22NySpPG4qsETA19sRa2e_ONBG%22%5D"],["FR-Pue","Puechabon","FR","ICOS","","ICOS","EBF",2000,2024,"https://data.icos-cp.eu/licence_accept?ids=%5B%225vx0Ks1CqWMCVA8BrWv_IDrV%22%5D"],["FR-Tou","Toulouse","FR","ICOS","","ICOS","GRA",2018,2024,"https://data.icos-cp.eu/licence_accept?ids=%5B%22LZSDmUp2MspQPIyTfDwNXYhi%22%5D"],["GF-Guy","Guyaflux","GF","ICOS","","ICOS","EBF",2017,2024,"https://data.icos-cp.eu/licence_accept?ids=%5B%223jDZZoDeBw29TRwEqPKQozcn%22%5D"],["GL-Dsk","Disko","GL","ICOS","","ICOS","OSH",2020,2024,"https://data.icos-cp.eu/licence_accept?ids=%5B%22c9E9mFx4AxSPu_Wb2l-pmMHm%22%5D"],["GL-NuF","Nuuk Fen","GL","ICOS","","ICOS","WET",2019,2024,"https://data.icos-cp.eu/licence_accept?ids=%5B%22EfhStDGazgCMZH4SX2aNUPlt%22%5D"],["GL-ZaF","Zackenberg Fen","GL","ICOS","","ICOS","WET",2023,2024,"https://data.icos-cp.eu/licence_accept?ids=%5B%22Lf3j25yaK_SzajN-sxvn-Mfj%22%5D"],["GL-ZaH","Zackenberg Gras","GL","ICOS","","ICOS","GRA",2020,2024,"https://data.icos-cp.eu/licence_accept?ids=%5B%22Zdiwv_V4gNbOfd5Bttpb-9q2%22%5D"],["ID-JOP","Jambi Oil Palm Plantation","ID","ICOS","","FLX","EBF",2014,2024,"https://data.icos-cp.eu/licence_accept?ids=%5B%22PPguZ8g7dO0HMK1i3qLRsXdQ%22%5D"],["ID-PaB","Palangkaraya Drained Burnt forest","ID","ICOS","","JPF","OSH",2004,2016,"https://data.icos-cp.eu/licence_accept?ids=%5B%22MpLHCY-ecJkBO48pW8l-Tra-%22%5D"],["ID-PaD","Palangkaraya Drained forest","ID","ICOS","","JPF","EBF",2001,2017,"https://data.icos-cp.eu/licence_accept?ids=%5B%22RaxQP0fkOSWCXKIIhi7Bnevj%22%5D"],["ID-Pag","Palangkaraya undrained forest","ID","ICOS","","JPF","EBF",2004,2018,"https://data.icos-cp.eu/licence_accept?ids=%5B%22I6zVvSdiWHZ4d2Bal9dhQhoi%22%5D"],["IL-RmH","Ramat Hanadiv","IL","ICOS","","EUF","EBF",2015,2020,"https://data.icos-cp.eu/licence_accept?ids=%5B%22BDfZZGumiN8Ci3FRoFGYGKdQ%22%5D"],["IL-Yat","Yatir","IL","ICOS","","EUF","ENF",2000,2024,"https://data.icos-cp.eu/licence_accept?ids=%5B%22ddBS_ZLjXuBI8SSQV2cskqda%22%5D"],["IT-Arz","Arzelle","IT","ICOS","","EUF","OSH",2016,2024,"https://data.icos-cp.eu/licence_accept?ids=%5B%22xK4i981ZSwQZHJeKKfpx5eZo%22%5D"],["IT-BFt","Bosco Fontana","IT","ICOS","","ICOS","DBF",2019,2024,"https://data.icos-cp.eu/licence_accept?ids=%5B%22IUOlBlndAhz4kdSgYJUDyq-D%22%5D"],["IT-BsB","Bussoleno Bosco","IT","ICOS","","EUF","DBF",2021,2024,"https://data.icos-cp.eu/licence_accept?ids=%5B%22m7FE4F9G5kn2XaEsWLMCtomo%22%5D"],["IT-Cp2","Castelporziano2","IT","ICOS","","ICOS","MF",2012,2024,"https://data.icos-cp.eu/licence_accept?ids=%5B%22B6lVx5OEcdr4ZS-3ix2K7iPP%22%5D"],["IT-Lsn","Lison","IT","ICOS","","ICOS","OSH",2016,2024,"https://data.icos-cp.eu/licence_accept?ids=%5B%22wjxZGQl8gUxBPVKPVlu4-g5L%22%5D"],["IT-MBo","Monte Bondone","IT","ICOS","","ICOS","GRA",2003,2024,"https://data.icos-cp.eu/licence_accept?ids=%5B%22E0wSFc1mB8oN23pHXtN2iH3Z%22%5D"],["IT-NiG","Nivolet grassland","IT","ICOS","","EUF","GRA",2020,2024,"https://data.icos-cp.eu/licence_accept?ids=%5B%22AFk3rC6RlVTrfbe2tNBYfSCG%22%5D"],["IT-Niv","Nivolet","IT","ICOS","","ICOS","GRA",2019,2024,"https://data.icos-cp.eu/licence_accept?ids=%5B%22KEdPYVMu2ozICBTFUa7oRkYX%22%5D"],["IT-Noe","Arca di Noe - Le Prigionette","IT","ICOS","","ICOS","CSH",2022,2024,"https://data.icos-cp.eu/licence_accept?ids=%5B%228Bb_KAh_eV1dOnGTW6OKP4n0%22%5D"],["IT-Ren","Renon","IT","ICOS","","ICOS","ENF",1999,2024,"https://data.icos-cp.eu/licence_accept?ids=%5B%22MneKjijlv5X9lwsAh_VHcJt6%22%5D"],["IT-SR2","San Rossore 2","IT","ICOS","","FLX","ENF",2013,2024,"https://data.icos-cp.eu/licence_accept?ids=%5B%22Frhkznd6pBhhJKKaYoAShaV2%22%5D"],["IT-Tor","Torgnon","IT","ICOS","","ICOS","GRA",2008,2024,"https://data.icos-cp.eu/licence_accept?ids=%5B%22jpLpilIX0DYcAXQubpEJEEBn%22%5D"],["IT-TrF","Torgnon-LD","IT","ICOS","","ICOS","DNF",2012,2024,"https://data.icos-cp.eu/licence_accept?ids=%5B%22YwbRGa_5X4xiWtFOUz2_TvxL%22%5D"],["JP-Api","Appi forest meteorology research site","JP","ICOS","","JPF","DBF",2000,2022,"https://data.icos-cp.eu/licence_accept?ids=%5B%22XJkjHunTJq8lHQgSa-wYjGL5%22%5D"],["JP-BBY","Bibai bog","JP","ICOS","","JPF","WET",2014,2020,"https://data.icos-cp.eu/licence_accept?ids=%5B%22pMEqkfODsJGzX9RKz9kSDRtA%22%5D"],["JP-Fhk","Fuji Hokuroku Flux Observation Site","JP","ICOS","","JPF","DNF",2006,2023,"https://data.icos-cp.eu/licence_accept?ids=%5B%225HO9DkOtLv80oPgti-3L_1gg%22%5D"],["JP-Fjy","Fujiyoshida forest meteorology research site","JP","ICOS","","JPF","ENF",2001,2021,"https://data.icos-cp.eu/licence_accept?ids=%5B%22rPUO8Mfj9nIziKi_4d2XRkCh%22%5D"],["JP-Fmt","Field Museum Tama Hills","JP","ICOS","","JPF","MF",2014,2023,"https://data.icos-cp.eu/licence_accept?ids=%5B%22eWDbJgVovrhZWWNoXdZwB1GA%22%5D"],["JP-Hc2","Hachihama Experimental Farm","JP","ICOS","","JPF","CRO",2003,2004,"https://data.icos-cp.eu/licence_accept?ids=%5B%22Tjd4S1VJ4LO2w5OrXE1eWhYl%22%5D"],["JP-Hc3","Hachihama Experimental Farm Double Crop","JP","ICOS","","JPF","CRO",2005,2008,"https://data.icos-cp.eu/licence_accept?ids=%5B%227mRmcdv3o0cDwldpdIkzLgqj%22%5D"],["JP-KaP","Kasumigaura lotus paddy","JP","ICOS","","JPF","CRO",1997,1997,"https://data.icos-cp.eu/licence_accept?ids=%5B%227QrnIdeknEjsBsGnEAcpIxqx%22%5D"],["JP-Khw","Kahoku Experiment watershed","JP","ICOS","","JPF","ENF",2000,2021,"https://data.icos-cp.eu/licence_accept?ids=%5B%22ws7GV5BLwsKMaGOsosxNThpD%22%5D"],["JP-Kzw","Karuizawa","JP","ICOS","","JPF","MF",2001,2008,"https://data.icos-cp.eu/licence_accept?ids=%5B%22heCzGI50bl4F9zNueG7UvN3S%22%5D"],["JP-MBF","Moshiri Birch Forest Site","JP","ICOS","","JPF","DBF",2004,2011,"https://data.icos-cp.eu/licence_accept?ids=%5B%22dP1aRNVfrf316N-6GTejUbIk%22%5D"],["JP-MMF","Moshiri Mixd Forest Site","JP","ICOS","","JPF","MF",2004,2011,"https://data.icos-cp.eu/licence_accept?ids=%5B%22Gq5ddm9JljmhtiELU0sAXSqu%22%5D"],["JP-Mse","Mase rice paddy field","JP","ICOS","","JPF","CRO",2002,2009,"https://data.icos-cp.eu/licence_accept?ids=%5B%22496cflc8MbepzdjJvLU5v4cg%22%5D"],["JP-NsC","NILGS Nasu Research Station Chemical Fertilizer Plot","JP","ICOS","","JPF","GRA",2004,2015,"https://data.icos-cp.eu/licence_accept?ids=%5B%229MJ6Rbkq1nwFkdiq96CdBSn_%22%5D"],["JP-NsM","NILGS Nasu Research Station Manure Application Plot","JP","ICOS","","JPF","GRA",2004,2015,"https://data.icos-cp.eu/licence_accept?ids=%5B%22qug7pUfVBqZPbH4yxh0PKfgu%22%5D"],["JP-Nuf","Nagoya University Forest","JP","ICOS","","JPF","DBF",2000,2001,"https://data.icos-cp.eu/licence_accept?ids=%5B%22rBNU9avgc7c4tNBrBRWVn22z%22%5D"],["JP-Om2","Farm field in Osaka Metropolitan University","JP","ICOS","","JPF","GRA",2022,2023,"https://data.icos-cp.eu/licence_accept?ids=%5B%22lsP2zCZJBUgW9PNkwls5Cb79%22%5D"],["JP-SMF","Seto Mixed Forest Site","JP","ICOS","","JPF","MF",2002,2014,"https://data.icos-cp.eu/licence_accept?ids=%5B%22OJmZUckooZnjzhPVMCBvUM85%22%5D"],["JP-Sb1","Sarobetsu Mire Moss","JP","ICOS","","JPF","WET",2007,2010,"https://data.icos-cp.eu/licence_accept?ids=%5B%22jOdJ40q12wURBzPC91Zd1Nrx%22%5D"],["JP-Sb2","Sarobetsu Mire Sasa","JP","ICOS","","JPF","WET",2007,2010,"https://data.icos-cp.eu/licence_accept?ids=%5B%22Pxix-JtRatuGLAPdOuOHUdzr%22%5D"],["JP-Shn","Shinshu University Experimental Forest Site","JP","ICOS","","JPF","MF",2014,2020,"https://data.icos-cp.eu/licence_accept?ids=%5B%222odGxi9yoGlFUuRSPP0IvuyH%22%5D"],["JP-Spp","Sapporo forest meteorology research site","JP","ICOS","","JPF","DBF",2000,2018,"https://data.icos-cp.eu/licence_accept?ids=%5B%22js_dXPMf2Ctz9mN3PGXCd2zb%22%5D"],["JP-Srk","Shirakami Beech Forest Site","JP","ICOS","","JPF","DBF",2010,2016,"https://data.icos-cp.eu/licence_accept?ids=%5B%22eFz2nv5isK9K_5qkLLh6xxAF%22%5D"],["JP-Ta2","Takayama evergreen coniferous forest site","JP","ICOS","","JPF","ENF",2005,2015,"https://data.icos-cp.eu/licence_accept?ids=%5B%22CmfB4bc3xT3z8lqsrgqLbIGm%22%5D"],["JP-Tak","Takayama deciduous broadleaf forest site","JP","ICOS","","JPF","DBF",1998,2021,"https://data.icos-cp.eu/licence_accept?ids=%5B%223ISWj-Lz0wAZ7bHcl0axSoWX%22%5D"],["JP-Tef","CC-LaG Teshio Experimental Forest","JP","ICOS","","JPF","DNF",2001,2023,"https://data.icos-cp.eu/licence_accept?ids=%5B%22U36jKvGfGICHSJO01Sk4jEZT%22%5D"],["JP-Tkb","Tsukuba Experimental Watershed","JP","ICOS","","JPF","ENF",2018,2019,"https://data.icos-cp.eu/licence_accept?ids=%5B%22DJQ3QbfTvEPAp9g4mpyX5ABJ%22%5D"],["JP-Tmd","Tomakomai Flux Research Site Disturbed","JP","ICOS","","JPF","GRA",2005,2023,"https://data.icos-cp.eu/licence_accept?ids=%5B%220o-e7G4yJgKYUrpjjLe7w0lt%22%5D"],["JP-Tmk","Tomakomai Flux Research Site","JP","ICOS","","JPF","DNF",2001,2003,"https://data.icos-cp.eu/licence_accept?ids=%5B%22bCOHeAK5zPgbC1DQddUjFOlA%22%5D"],["JP-Yms","Yamashiro forest meteorology research site","JP","ICOS","","JPF","DBF",2000,2023,"https://data.icos-cp.eu/licence_accept?ids=%5B%22fI4RJEyaI5ASWeYLUEHZddaP%22%5D"],["JP-Ynf","Yona-Field Tower Site","JP","ICOS","","JPF","EBF",2013,2022,"https://data.icos-cp.eu/licence_accept?ids=%5B%22Z6-dU8nagfkiCVVyjdnFCe5b%22%5D"],["KE-Aq1","Ausquest 1","KE","ICOS","","FLX","CRO",2019,2019,"https://data.icos-cp.eu/licence_accept?ids=%5B%22i4EXIipasIDWP9d8IyG0XJjN%22%5D"],["KE-Aq2","Ausquest 2","KE","ICOS","","FLX","CRO",2022,2024,"https://data.icos-cp.eu/licence_accept?ids=%5B%22QFscsSwywYpuelYVvg63oaJu%22%5D"],["KE-Kpt","Kapiti","KE","ICOS","","FLX","GRA",2018,2024,"https://data.icos-cp.eu/licence_accept?ids=%5B%22NIXGBI6SVBOylbOHTxoujI4u%22%5D"],["KE-Mkt","Maktau","KE","ICOS","","FLX","CRO",2019,2024,"https://data.icos-cp.eu/licence_accept?ids=%5B%22-dDx4tGmNR4X0U5IZ1WtSjW_%22%5D"],["KH-Kmp","Kampong Thom Lowland Dry Evergreen Forest","KH","ICOS","","JPF","EBF",2011,2014,"https://data.icos-cp.eu/licence_accept?ids=%5B%227HZxy0gTRodMZnmJU6ak4vHi%22%5D"],["KR-AdC","Anmyeondo Coniferous forest","KR","ICOS","","KOF","ENF",2015,2018,"https://data.icos-cp.eu/licence_accept?ids=%5B%22m5QvlBnkK_hdAFCUpmGPzXTI%22%5D"],["KR-CRK","Cheorwon Rice paddy","KR","ICOS","","KOF","CRO",2015,2021,"https://data.icos-cp.eu/licence_accept?ids=%5B%22H8OP2ngO7ZJkZ087BV4UNehk%22%5D"],["KR-CmF","Cheongmicheon Farmland","KR","ICOS","","KOF","CRO",2012,2019,"https://data.icos-cp.eu/licence_accept?ids=%5B%229yCK9zGwG8buI8JKtUWmROLY%22%5D"],["KR-GmP","Gimje Rice-barley double cropping Paddy Field","KR","ICOS","","KOF","CRO",2011,2014,"https://data.icos-cp.eu/licence_accept?ids=%5B%220TTeq3pvvIas1NLdD2HMvWMC%22%5D"],["KR-GmR","Gimje Rice Paddy","KR","ICOS","","KOF","CRO",2017,2019,"https://data.icos-cp.eu/licence_accept?ids=%5B%22Ssyo985v7h7CTmNEtvwTbQsE%22%5D"],["KR-GmS","Gimje Soybean Field","KR","ICOS","","KOF","CRO",2017,2019,"https://data.icos-cp.eu/licence_accept?ids=%5B%225Kb3vNI8mqBd_eETiy2wuWSK%22%5D"],["KR-HPK","Haenam Paddy-field","KR","ICOS","","KOF","CRO",2016,2018,"https://data.icos-cp.eu/licence_accept?ids=%5B%22zfSFiNxBUci2ScUx6BSMynNA%22%5D"],["KR-HcM","Hongcheon Mixed forest","KR","ICOS","","KOF","MF",2015,2018,"https://data.icos-cp.eu/licence_accept?ids=%5B%22j9Kwyg7s5TpieDfvx4qg9WSR%22%5D"],["KR-Hnm","Haenam Farmland (HFK)","KR","ICOS","","KOF","CRO",2016,2019,"https://data.icos-cp.eu/licence_accept?ids=%5B%226juxi14AX0CYmbd3rABrd8Qg%22%5D"],["KR-JjM","Jeju Mixed forest","KR","ICOS","","KOF","MF",2015,2018,"https://data.icos-cp.eu/licence_accept?ids=%5B%22Wq4UZR5CnT0upivSDf3D8uUc%22%5D"],["KR-Kw1","Gwangneung Coniferous forest","KR","ICOS","","KOF","ENF",2016,2020,"https://data.icos-cp.eu/licence_accept?ids=%5B%221RvfmPwtVEtfGXXUyFU-U7CT%22%5D"],["KR-Kw2","Gwangneung Deciduous forest","KR","ICOS","","KOF","DBF",2016,2020,"https://data.icos-cp.eu/licence_accept?ids=%5B%22n2qEvY4a79bHgLKrB0qipAJ_%22%5D"],["KR-Nj1","Naju Rice Paddy 1","KR","ICOS","","KOF","CRO",2023,2024,"https://data.icos-cp.eu/licence_accept?ids=%5B%22ho-3zaqsi4UTaFuVjoKo6tcK%22%5D"],["KR-Nj2","Naju Rice Paddy 2","KR","ICOS","","KOF","CRO",2023,2024,"https://data.icos-cp.eu/licence_accept?ids=%5B%22o9_1GTQfYPO5QensOTM6NVIz%22%5D"],["KR-PcD","Pyeongchang Deciduous forest","KR","ICOS","","KOF","DBF",2015,2018,"https://data.icos-cp.eu/licence_accept?ids=%5B%224wKzVD2bJxwyGKiuPS3-bBLW%22%5D"],["KR-ScC","Samcheok Coniferous forest","KR","ICOS","","KOF","ENF",2015,2018,"https://data.icos-cp.eu/licence_accept?ids=%5B%226dwzloq1r3LGTyJ3wGCMxk0C%22%5D"],["KR-SmM","Seolmacheon Mixed forest","KR","ICOS","","KOF","MF",2015,2021,"https://data.icos-cp.eu/licence_accept?ids=%5B%22VK7v0BF3ASSyw7wQ9MoSmq5T%22%5D"],["KR-TwB","Taehwa Broadleaf forest","KR","ICOS","","KOF","DBF",2024,2024,"https://data.icos-cp.eu/licence_accept?ids=%5B%22mgAw4w8tckxD-oe0sc6ng63R%22%5D"],["KR-TwC","Taehwa Coniferous forest","KR","ICOS","","KOF","ENF",2024,2024,"https://data.icos-cp.eu/licence_accept?ids=%5B%22GrvLMNKKbTTAaT6auJyS_xJj%22%5D"],["KR-UAO","Uiseong Apple Orchard","KR","ICOS","","KOF","CRO",2017,2019,"https://data.icos-cp.eu/licence_accept?ids=%5B%22_55n5cfT3PjNVp8hjP7P_GLa%22%5D"],["KR-WdE","Wando Evergreen broadleaf forest","KR","ICOS","","KOF","EBF",2015,2018,"https://data.icos-cp.eu/licence_accept?ids=%5B%22eX7IFzdl2WPUmwGiAQ3UI6RD%22%5D"],["MN-Hst","Hustai grassland","MN","ICOS","","JPF","GRA",2015,2020,"https://data.icos-cp.eu/licence_accept?ids=%5B%2213XztQKfZ_zocPMte-r5AtGa%22%5D"],["MN-Kbu","Kherlenbayan Ulaan","MN","ICOS","","JPF","GRA",2003,2008,"https://data.icos-cp.eu/licence_accept?ids=%5B%22qboNh8q5SAEz1-NZO2ZA_s6V%22%5D"],["MN-Nkh","Nalaikh grassland","MN","ICOS","","JPF","GRA",2015,2020,"https://data.icos-cp.eu/licence_accept?ids=%5B%22wOMUKsoUO8-izEp_YKLHLZCH%22%5D"],["MN-Udg","Udleg practice forest","MN","ICOS","","JPF","DNF",2010,2012,"https://data.icos-cp.eu/licence_accept?ids=%5B%22zPXpxhbjz_GLVPOMGg_bGCuF%22%5D"],["MY-LHP","Lambir Hills National Park","MY","ICOS","","JPF","EBF",2009,2019,"https://data.icos-cp.eu/licence_accept?ids=%5B%22ug2smfKpeFuNSWo-g_LKn8R4%22%5D"],["NL-Hrw","Haarweg","NL","ICOS","","EUF","GRA",2001,2010,"https://data.icos-cp.eu/licence_accept?ids=%5B%222n9K8BG8bbK4xGh7uz6Di8Rm%22%5D"],["NL-Loo","Loobos","NL","ICOS","","ICOS","ENF",1997,2024,"https://data.icos-cp.eu/licence_accept?ids=%5B%22WewhyVCaeifJzeZN8L6CdbW3%22%5D"],["NL-Vkp","Veenkampen","NL","ICOS","","EUF","GRA",2014,2024,"https://data.icos-cp.eu/licence_accept?ids=%5B%22yIhmJsmZaC0uHAABPhF1WTWL%22%5D"],["NO-Fns","Finse","NO","ICOS","","EUF","SNO",2017,2024,"https://data.icos-cp.eu/licence_accept?ids=%5B%22kDrWIYdOIg7jxi4gGpiV2vMK%22%5D"],["NO-Hur","Hurdal","NO","ICOS","","ICOS","ENF",2023,2024,"https://data.icos-cp.eu/licence_accept?ids=%5B%22YCEzlpvXRhpZaAf8MW92lLOf%22%5D"],["NO-Ikr","Iskoras","NO","ICOS","","EUF","WET",2019,2022,"https://data.icos-cp.eu/licence_accept?ids=%5B%228LmO1TBatCif6_LoU8kHEcPy%22%5D"],["RU-Ch2","Cherski reference","RU","ICOS","","EUF","WET",2014,2021,"https://data.icos-cp.eu/licence_accept?ids=%5B%223xSmQwrTa-Ufn-rKi86qwxkR%22%5D"],["RU-Ege","Elgeeii forest station","RU","ICOS","","JPF","DNF",2010,2018,"https://data.icos-cp.eu/licence_accept?ids=%5B%22b5nU8v8vNcUd71xRKtWQdbLl%22%5D"],["RU-Fy2","Fyodorovskoye dry spruce stand","RU","ICOS","","EUF","ENF",2015,2024,"https://data.icos-cp.eu/licence_accept?ids=%5B%22Vh2pWjfw5HPNZJDA6XfQSvcP%22%5D"],["RU-Fy4","Fyodorovskoye bog","RU","ICOS","","EUF","WET",2015,2020,"https://data.icos-cp.eu/licence_accept?ids=%5B%22hItM4WCQqnQ68mQo9OvhTd6F%22%5D"],["RU-Fyo","Fyodorovskoye","RU","ICOS","","EUF","ENF",1998,2024,"https://data.icos-cp.eu/licence_accept?ids=%5B%22GW1i5FQInU-IW_0iisGVDXW3%22%5D"],["RU-NeB","Neleger Burnt Forest","RU","ICOS","","JPF","GRA",1999,2000,"https://data.icos-cp.eu/licence_accept?ids=%5B%2262X8tlaZVNU1oh_okQKPco3F%22%5D"],["RU-NeC","Neleger Cutover","RU","ICOS","","JPF","OSH",2001,2006,"https://data.icos-cp.eu/licence_accept?ids=%5B%22BGkXJsSt5UVy1vDEw7Z30_7v%22%5D"],["RU-NeF","Neleger larch forest","RU","ICOS","","JPF","DNF",2000,2006,"https://data.icos-cp.eu/licence_accept?ids=%5B%22MTJpX3fgVsWfWNXaw59q41td%22%5D"],["RU-Sk2","Yakutsk Spasskaya Pad Pine","RU","ICOS","","JPF","ENF",2004,2008,"https://data.icos-cp.eu/licence_accept?ids=%5B%22gHfX6bXPIDHzHbwVE7gWolFT%22%5D"],["RU-SkP","Yakutsk Spasskaya Pad larch","RU","ICOS","","JPF","DNF",2004,2014,"https://data.icos-cp.eu/licence_accept?ids=%5B%22EQli39tXbluFl81vRolYNGMQ%22%5D"],["RU-Tur","Tura","RU","ICOS","","JPF","DNF",2004,2004,"https://data.icos-cp.eu/licence_accept?ids=%5B%22Rd4_p0MUa-ttK6FzOMLontdl%22%5D"],["SE-Deg","Degero","SE","ICOS","","ICOS","WET",2019,2024,"https://data.icos-cp.eu/licence_accept?ids=%5B%22IiyJGdmPkDhdItxg1_8lgLFp%22%5D"],["SE-Htm","Hyltemossa","SE","ICOS","","ICOS","ENF",2018,2024,"https://data.icos-cp.eu/licence_accept?ids=%5B%228hMY0lY7kERIfokXkEpev-03%22%5D"],["SE-Nor","Norunda","SE","ICOS","","ICOS","ENF",2018,2024,"https://data.icos-cp.eu/licence_accept?ids=%5B%22TQJ13O19n72qJ3MoGHnXCdRB%22%5D"],["SE-Sto","Abisko-Stordalen Palsa Bog","SE","ICOS","","ICOS","WET",2022,2024,"https://data.icos-cp.eu/licence_accept?ids=%5B%22gROMoDY5jMLhMTRejjKXtC-s%22%5D"],["SE-Svb","Svartberget","SE","ICOS","","ICOS","ENF",2014,2024,"https://data.icos-cp.eu/licence_accept?ids=%5B%22SxJ5MBCJuCmHLPK4C1fgwGCc%22%5D"],["SE-Trb","Trollberget","SE","ICOS","","EUF","WET",2021,2023,"https://data.icos-cp.eu/licence_accept?ids=%5B%22zZioWvKJVU9_vq3xFG9pr7F7%22%5D"],["SN-Dhr","Dahra","SN","ICOS","","EUF","GRA",2010,2022,"https://data.icos-cp.eu/licence_accept?ids=%5B%22KdzlABR5BBUtxi1T7yzDK4_Z%22%5D"],["SN-Nkr","Niakhar","SN","ICOS","","EUF","CRO",2018,2024,"https://data.icos-cp.eu/licence_accept?ids=%5B%22X5l5NTHw0ymH6hudWtJMskZe%22%5D"],["TH-Kog","Kog-Ma Wateshed","TH","ICOS","","JPF","EBF",2005,2013,"https://data.icos-cp.eu/licence_accept?ids=%5B%22UeiwpE7b8yxM3HJis9B-clmg%22%5D"],["TH-Mae","Mae Moh plantation","TH","ICOS","","JPF","DBF",2005,2016,"https://data.icos-cp.eu/licence_accept?ids=%5B%22xAfMteUmc_R9X2IXVuuRkSa3%22%5D"],["UK-AMo","Auchencorth Moss","UK","ICOS","","ICOS","WET",2003,2024,"https://data.icos-cp.eu/licence_accept?ids=%5B%22bUNge2BcADhYDR1h9NHDXbem%22%5D"],["UK-Ags","Anglesey","UK","ICOS","","EUF","GRA",2023,2024,"https://data.icos-cp.eu/licence_accept?ids=%5B%2284y7MrbQ3ZSBKr4Kv-0_fdiY%22%5D"],["UK-BnB","Ballynahone Bog","UK","ICOS","","EUF","GRA",2021,2024,"https://data.icos-cp.eu/licence_accept?ids=%5B%22QBlY2INal0mc2mRsgN9Wr_CV%22%5D"],["UK-CCr","Cors Caron","UK","ICOS","","EUF","GRA",2022,2024,"https://data.icos-cp.eu/licence_accept?ids=%5B%22LrO8fItItMas7E62Hm_A032I%22%5D"],["UK-Cvn","Coveney","UK","ICOS","","EUF","GRA",2023,2024,"https://data.icos-cp.eu/licence_accept?ids=%5B%2237X3GrWRM7AEcdIt8WRasg1l%22%5D"],["UK-GaB","Garry Bog","UK","ICOS","","EUF","GRA",2022,2024,"https://data.icos-cp.eu/licence_accept?ids=%5B%223ur3ylHM5TMBuyVRXci8ohT_%22%5D"],["UK-Gnn","Glenullin","UK","ICOS","","EUF","GRA",2022,2024,"https://data.icos-cp.eu/licence_accept?ids=%5B%22rr5GFzsDarjbHdARWXryBopk%22%5D"],["UK-Gwr","Glenwherry","UK","ICOS","","EUF","GRA",2022,2024,"https://data.icos-cp.eu/licence_accept?ids=%5B%22kdw13mqVIM_fuCSUoFjwLTBX%22%5D"],["UK-HgF","High Fen","UK","ICOS","","EUF","GRA",2023,2024,"https://data.icos-cp.eu/licence_accept?ids=%5B%220bh_V0qcsU1jVRdLmTN38MrV%22%5D"],["UK-HpF","Hope Farm","UK","ICOS","","EUF","CRO",2023,2024,"https://data.icos-cp.eu/licence_accept?ids=%5B%229XNveiBJ_2A4uYC0hHFDy3RS%22%5D"],["VU-Coc","Cocoflux","VU","ICOS","","FLX","EBF",2001,2004,"https://data.icos-cp.eu/licence_accept?ids=%5B%22PrWE9DMXpEen7ZyDmWcJ1EnX%22%5D"],["ZA-BfK","Benfontien Karoo","ZA","ICOS","","SAEON","OSH",2020,2024,"https://data.icos-cp.eu/licence_accept?ids=%5B%22L3b447DFrFAeO56M1P7eueuq%22%5D"],["ZA-BfS","Benfontien Savanna","ZA","ICOS","","SAEON","OSH",2020,2024,"https://data.icos-cp.eu/licence_accept?ids=%5B%227D87eYcefMtCZ131SjGfAEvu%22%5D"],["ZA-Jks","Jonkershoek","ZA","ICOS","","SAEON","GRA",2024,2024,"https://data.icos-cp.eu/licence_accept?ids=%5B%22pJ8V89PtIUTciotXGRT7PLki%22%5D"],["ZA-Spk","Spioenkop","ZA","ICOS","","SAEON","GRA",2023,2024,"https://data.icos-cp.eu/licence_accept?ids=%5B%229DBU3ZCobRStxNAcLBAZVtok%22%5D"],["ZA-Uby","Umhlabuyalingana","ZA","ICOS","","SAEON","GRA",2023,2024,"https://data.icos-cp.eu/licence_accept?ids=%5B%22STLJfs_nkGgsI6sPzHNIgYE0%22%5D"],["AU-ASM","Alice Springs Mulga","AU","TERN","TERN","TERN","SAV",2010,2024,"https://dap.tern.org.au/thredds/fileServer/ecosystem_process/fluxnet/2025_r1/TERN_AU-ASM_FLUXNET_2010-2024_v1.3_r1.zip"],["AU-Ade","Adelaide River","AU","TERN","OzFlux","TERN","WSA",2007,2009,"https://dap.tern.org.au/thredds/fileServer/ecosystem_process/fluxnet/2025_r1/TERN_AU-Ade_FLUXNET_2007-2009_v1.3_r1.zip"],["AU-Boy","Boyagin","AU","TERN","TERN","TERN","WSA",2017,2024,"https://dap.tern.org.au/thredds/fileServer/ecosystem_process/fluxnet/2025_r1/TERN_AU-Boy_FLUXNET_2017-2024_v1.3_r1.zip"],["AU-Cpr","Calperum Chowilla","AU","TERN","TERN","TERN","SAV",2010,2024,"https://dap.tern.org.au/thredds/fileServer/ecosystem_process/fluxnet/2025_r1/TERN_AU-Cpr_FLUXNET_2010-2024_v1.3_r1.zip"],["AU-Cum","Cumberland Plain","AU","TERN","TERN","TERN","CVM",2014,2024,"https://dap.tern.org.au/thredds/fileServer/ecosystem_process/fluxnet/2025_r1/TERN_AU-Cum_FLUXNET_2014-2024_v1.3_r1.zip"],["AU-Lox","Loxton Eddy Covariance Site","AU","TERN","OzFlux","TERN","DBF",2008,2009,"https://dap.tern.org.au/thredds/fileServer/ecosystem_process/fluxnet/2025_r1/TERN_AU-Lox_FLUXNET_2008-2009_v1.3_r1.zip"],["AU-Wom","Wombat Forest","AU","TERN","TERN","TERN","EBF",2010,2024,"https://dap.tern.org.au/thredds/fileServer/ecosystem_process/fluxnet/2025_r1/TERN_AU-Wom_FLUXNET_2010-2024_v1.3_r1.zip"],["NZ-ADd","Ashley Dene dry","NZ","TERN","OzFlux","TERN","CRO",2016,2018,"https://dap.tern.org.au/thredds/fileServer/ecosystem_process/fluxnet/2025_r1/TERN_NZ-ADd_FLUXNET_2016-2018_v1.3_r1.zip"],["NZ-ADw","Ashley Dene wet","NZ","TERN","OzFlux","TERN","CRO",2015,2018,"https://dap.tern.org.au/thredds/fileServer/ecosystem_process/fluxnet/2025_r1/TERN_NZ-ADw_FLUXNET_2015-2018_v1.3_r1.zip"]]}